{
  "strategy": "Favorite Follower (NO at 91-97c)",
  "original_claim": {
    "markets": 311,
    "win_rate": 0.952,
    "roi": 0.0493
  },
  "retest_results": {
    "n_markets": 18690,
    "win_rate": 0.9692883895131086,
    "avg_no_price": 94.4295990894393,
    "breakeven": 0.944295990894393,
    "edge": 0.024992398618715606,
    "p_value": 0.0
  },
  "concentration": {
    "top_10_pct": 0.20911148665991589,
    "pass": true
  },
  "price_proxy_analysis": {
    "bucket_results": [
      {
        "bucket": 91,
        "baseline_wr": 0.9469983775013521,
        "signal_wr": 0.9461756373937678,
        "improvement": -0.0008227401075843188,
        "n_signal": 1765,
        "n_baseline": 1849
      },
      {
        "bucket": 92,
        "baseline_wr": 0.952752492414391,
        "signal_wr": 0.952752492414391,
        "improvement": 0.0,
        "n_signal": 2307,
        "n_baseline": 2307
      },
      {
        "bucket": 93,
        "baseline_wr": 0.9583333333333334,
        "signal_wr": 0.9583333333333334,
        "improvement": 0.0,
        "n_signal": 2376,
        "n_baseline": 2376
      },
      {
        "bucket": 94,
        "baseline_wr": 0.9724665391969407,
        "signal_wr": 0.9724665391969407,
        "improvement": 0.0,
        "n_signal": 2615,
        "n_baseline": 2615
      },
      {
        "bucket": 95,
        "baseline_wr": 0.9697542533081286,
        "signal_wr": 0.9697542533081286,
        "improvement": 0.0,
        "n_signal": 2645,
        "n_baseline": 2645
      },
      {
        "bucket": 96,
        "baseline_wr": 0.9802551640340219,
        "signal_wr": 0.9802551640340219,
        "improvement": 0.0,
        "n_signal": 3292,
        "n_baseline": 3292
      },
      {
        "bucket": 97,
        "baseline_wr": 0.9855301236516706,
        "signal_wr": 0.9853658536585366,
        "improvement": -0.00016426999313401414,
        "n_signal": 3690,
        "n_baseline": 3801
      }
    ],
    "positive_buckets": 0,
    "total_buckets": 7,
    "weighted_improvement": -0.00011012801308458187,
    "is_price_proxy": true
  },
  "temporal_stability": {
    "quarter_results": [
      {
        "quarter": 1,
        "n": 16992,
        "win_rate": 0.9682203389830508,
        "breakeven": 0.9444546659396705,
        "edge": 0.023765673043380287
      },
      {
        "quarter": 2,
        "n": 1607,
        "win_rate": 0.9800871188550093,
        "breakeven": 0.9426270344533281,
        "edge": 0.03746008440168125
      },
      {
        "quarter": 3,
        "n": 76,
        "win_rate": 0.9736842105263158,
        "breakeven": 0.9442541353209818,
        "edge": 0.029430075205334028
      },
      {
        "quarter": 4,
        "n": 15,
        "win_rate": 1.0,
        "breakeven": 0.9435618345618346,
        "edge": 0.05643816543816538
      }
    ],
    "positive_quarters": 4
  },
  "validation_checks": {
    "n_markets_pass": true,
    "edge_positive": true,
    "p_value_pass": true,
    "concentration_pass": true,
    "not_price_proxy": false,
    "temporal_stable": true
  },
  "verdict": "REJECTED - PRICE PROXY",
  "reason": "Signal improvement of -0.01% vs baseline at same prices",
  "timestamp": "2025-12-29T17:40:11.247493"
}